hAMRonization/AbricateIO.py
hAMRonization/AmrFinderPlusIO.py
hAMRonization/AmrPlusPlusIO.py
hAMRonization/AribaIO.py
hAMRonization/CSStarIO.py
hAMRonization/DeepArgIO.py
hAMRonization/FARGeneIO.py
hAMRonization/GrootIO.py
hAMRonization/Interfaces.py
hAMRonization/KmerResistanceIO.py
hAMRonization/MykrobeIO.py
hAMRonization/ResFamsIO.py
hAMRonization/ResFinderIO.py
hAMRonization/RgiIO.py
hAMRonization/SraxIO.py
hAMRonization/Srst2IO.py
hAMRonization/StarAmrIO.py
hAMRonization/TBProfilerIO.py
hAMRonization/__init__.py
hAMRonization/constants.py
hAMRonization/hAMRonizedResult.py
hAMRonization/hamronize.py
hAMRonization/summarize.py
hamronization-1.1.9.dist-info/licenses/LICENSE.txt
hamronization-1.1.9.dist-info/METADATA
hamronization-1.1.9.dist-info/WHEEL
hamronization-1.1.9.dist-info/entry_points.txt
hamronization-1.1.9.dist-info/top_level.txt
hamronization-1.1.9.dist-info/zip-safe
hamronization-1.1.9.dist-info/RECORD
