Metadata-Version: 2.4
Name: hAMRonization
Version: 1.1.9
Summary: Tool to convert and summarize AMR gene detection outputs using the hAMRonization specification
Home-page: https://github.com/pha4ge/hAMRonization
Download-URL: https://github.com/pha4ge/archive/v1.1.9.tar.gz
Author: Finlay Maguire
Author-email: finlaymaguire@gmail.com
License: LGPLv3
Keywords: Genomics,Antimicrobial resistance,Antibiotic,Standardization
Classifier: Development Status :: 5 - Production/Stable
Classifier: Environment :: Console
Classifier: License :: OSI Approved :: GNU Lesser General Public License v3 (LGPLv3)
Classifier: Natural Language :: English
Classifier: Operating System :: MacOS
Classifier: Operating System :: POSIX
Classifier: Operating System :: POSIX :: Linux
Classifier: Programming Language :: Python :: 3
Classifier: Programming Language :: Python :: 3.7
Classifier: Programming Language :: Python :: 3.8
Classifier: Programming Language :: Python :: 3.9
Classifier: Intended Audience :: Science/Research
Classifier: Intended Audience :: Healthcare Industry
Classifier: Topic :: Scientific/Engineering :: Bio-Informatics
Requires-Python: >=3.7
License-File: LICENSE.txt
Requires-Dist: pandas
Dynamic: author
Dynamic: author-email
Dynamic: classifier
Dynamic: description
Dynamic: description-content-type
Dynamic: download-url
Dynamic: home-page
Dynamic: keywords
Dynamic: license
Dynamic: license-file
Dynamic: requires-dist
Dynamic: requires-python
Dynamic: summary
